{
  "id": "shakespeare-the-rape-of-lucrece",
  "title": "THE RAPE OF LUCRECE",
  "author": "William Shakespeare",
  "genre": "Classics",
  "coverColor": "linear-gradient(135deg, #06b6d4 0%, #0891b2 100%)",
  "description": "A classic masterpiece by William Shakespeare. Read this Project Gutenberg edition on Bakbak.store.",
  "chapters": [
    {
      "title": "Section 1",
      "file": "01_Section_1.md"
    },
    {
      "title": "Section 2",
      "file": "02_Section_2.md"
    },
    {
      "title": "Section 3",
      "file": "03_Section_3.md"
    },
    {
      "title": "Section 4",
      "file": "04_Section_4.md"
    },
    {
      "title": "Section 5",
      "file": "05_Section_5.md"
    },
    {
      "title": "Section 6",
      "file": "06_Section_6.md"
    }
  ]
}