{
  "id": "shakespeare-a-midsummer-nights-dream",
  "title": "A MIDSUMMER NIGHT\u2019S DREAM",
  "author": "William Shakespeare",
  "genre": "Classics",
  "coverColor": "linear-gradient(135deg, #ec4899 0%, #be185d 100%)",
  "description": "A classic masterpiece by William Shakespeare. Read this Project Gutenberg edition on Bakbak.store.",
  "chapters": [
    {
      "title": "Introduction",
      "file": "01_Introduction.md"
    },
    {
      "title": "The Same. A Room in a Cottage",
      "file": "02_The_Same__A_Room_in_a_Cottage.md"
    },
    {
      "title": "Another part of the wood",
      "file": "03_Another_part_of_the_wood.md"
    },
    {
      "title": "Scene I.",
      "file": "04_Scene_I.md"
    },
    {
      "title": "Another part of the wood",
      "file": "05_Another_part_of_the_wood.md"
    },
    {
      "title": "Athens. A Room in Quince\u2019s House",
      "file": "06_Athens__A_Room_in_Quince_s_Hou.md"
    },
    {
      "title": "Athens. An Apartment in the Palace of Theseus",
      "file": "07_Athens__An_Apartment_in_the_Pa.md"
    },
    {
      "title": "Dramatis Person\u00e6",
      "file": "08_Dramatis_Person.md"
    },
    {
      "title": "PHILOSTRATE, Master of the Revels to Theseus",
      "file": "09_PHILOSTRATE__Master_of_the_Rev.md"
    },
    {
      "title": "STARVELING, the Tailor",
      "file": "10_STARVELING__the_Tailor.md"
    },
    {
      "title": "MUSTARDSEED, Fairy",
      "file": "11_MUSTARDSEED__Fairy.md"
    },
    {
      "title": "performed by the Clowns",
      "file": "12_performed_by_the_Clowns.md"
    },
    {
      "title": "Attendants on Theseus and Hippolyta",
      "file": "13_Attendants_on_Theseus_and_Hipp.md"
    },
    {
      "title": "SCENE: Athens, and a wood not far from it",
      "file": "14_SCENE__Athens__and_a_wood_not.md"
    },
    {
      "title": "ACT I",
      "file": "15_ACT_I.md"
    },
    {
      "title": "SCENE I. Athens. A room in the Palace of Theseus",
      "file": "16_SCENE_I__Athens__A_room_in_the.md"
    },
    {
      "title": "Like to a step-dame or a dowager,",
      "file": "17_Like_to_a_step_dame_or_a_dowag.md"
    },
    {
      "title": "New bent in heaven, shall behold the night",
      "file": "18_New_bent_in_heaven__shall_beho.md"
    },
    {
      "title": "Turn melancholy forth to funerals;",
      "file": "19_Turn_melancholy_forth_to_funer.md"
    },
    {
      "title": "SCENE II. The Same. A Room in a Cottage",
      "file": "20_SCENE_II__The_Same__A_Room_in.md"
    },
    {
      "title": "ACT II",
      "file": "21_ACT_II.md"
    },
    {
      "title": "SCENE I. A wood near Athens",
      "file": "22_SCENE_I__A_wood_near_Athens.md"
    },
    {
      "title": "SCENE II. Another part of the wood",
      "file": "23_SCENE_II__Another_part_of_the.md"
    },
    {
      "title": "ACT III",
      "file": "24_ACT_III.md"
    },
    {
      "title": "SCENE I. The Wood.",
      "file": "25_SCENE_I__The_Wood.md"
    },
    {
      "title": "SCENE II. Another part of the wood",
      "file": "26_SCENE_II__Another_part_of_the.md"
    },
    {
      "title": "ACT IV",
      "file": "27_ACT_IV.md"
    },
    {
      "title": "SCENE I. The Wood",
      "file": "28_SCENE_I__The_Wood.md"
    },
    {
      "title": "SCENE II. Athens. A Room in Quince\u2019s House",
      "file": "29_SCENE_II__Athens__A_Room_in_Qu.md"
    },
    {
      "title": "ACT V",
      "file": "30_ACT_V.md"
    },
    {
      "title": "SCENE I. Athens. An Apartment in the Palace of Theseus",
      "file": "31_SCENE_I__Athens__An_Apartment.md"
    },
    {
      "title": "PROLOGUE",
      "file": "32_PROLOGUE.md"
    },
    {
      "title": "PROLOGUE",
      "file": "33_PROLOGUE.md"
    }
  ]
}